ubuntu_cloud_image_changelog/__init__.py
ubuntu_cloud_image_changelog/cli.py
ubuntu_cloud_image_changelog/conftest.py
ubuntu_cloud_image_changelog/launchpadagent.py
ubuntu_cloud_image_changelog/lib.py
ubuntu_cloud_image_changelog/models.py
ubuntu_cloud_image_changelog/tests/__init__.py
ubuntu_cloud_image_changelog/tests/test_get_cve_details.py
ubuntu_cloud_image_changelog/tests/test_input_models.py
ubuntu_cloud_image_changelog/tests/test_lib.py
ubuntu_cloud_image_changelog/tests/test_retry.py
ubuntu_cloud_image_changelog-0.15.7.dist-info/AUTHORS.rst
ubuntu_cloud_image_changelog-0.15.7.dist-info/LICENSE
ubuntu_cloud_image_changelog-0.15.7.dist-info/METADATA
ubuntu_cloud_image_changelog-0.15.7.dist-info/WHEEL
ubuntu_cloud_image_changelog-0.15.7.dist-info/entry_points.txt
ubuntu_cloud_image_changelog-0.15.7.dist-info/top_level.txt
ubuntu_cloud_image_changelog-0.15.7.dist-info/RECORD
