Metadata-Version: 2.1
Name: ubuntu-cloud-image-changelog
Version: 0.15.7
Summary: Helpful utility to generate package changelog between two cloud images
Home-page: https://github.com/CanonicalLtd/ubuntu-cloud-image-changelog
Author: Philip Roche
Author-email: cpc@groups.canonical.com
License: GNU General Public License v3
Keywords: ubuntu_cloud_image_changelog
Platform: UNKNOWN
Classifier: Development Status :: 2 - Pre-Alpha
Classifier: Intended Audience :: Developers
Classifier: License :: OSI Approved :: GNU General Public License v3 (GPLv3)
Classifier: Natural Language :: English
Classifier: Programming Language :: Python :: 3
Classifier: Programming Language :: Python :: 3.5
Classifier: Programming Language :: Python :: 3.6
Classifier: Programming Language :: Python :: 3.7
Classifier: Programming Language :: Python :: 3.8
Requires-Python: >=3.5
Requires-Dist: Click>=7.0
Requires-Dist: colorama
Requires-Dist: launchpadlib
Requires-Dist: pydantic>=2
Requires-Dist: python-debian
